carlschader_ml_utils/__init__.py
carlschader_ml_utils/embedding_utils.py
carlschader_ml_utils/image_utils.py
carlschader_ml_utils-0.4.6.dist-info/LICENSE
carlschader_ml_utils-0.4.6.dist-info/METADATA
carlschader_ml_utils-0.4.6.dist-info/WHEEL
carlschader_ml_utils-0.4.6.dist-info/top_level.txt
carlschader_ml_utils-0.4.6.dist-info/RECORD
